lhcb_rex/__init__.py
lhcb_rex/py.typed
lhcb_rex/data/data_handler.py
lhcb_rex/data/data_handlerGENERALISED.py
lhcb_rex/data/data_manager.py
lhcb_rex/data/graph_maker.py
lhcb_rex/data/loader.py
lhcb_rex/data/batch/make_graphs_batch.py
lhcb_rex/data/batch/submit_tools.py
lhcb_rex/inference/inference_graph_constructor.py
lhcb_rex/inference/inference_network_manager.py
lhcb_rex/inference/params.py
lhcb_rex/inference/run_network.py
lhcb_rex/inference/runner.py
lhcb_rex/models/hetero_graph_based_GAN.py
lhcb_rex/models/hetero_graph_based_GAN_smearing.py
lhcb_rex/models/hetero_graph_based_VAE_smearing.py
lhcb_rex/models/hetero_graph_based_diffusion_model.py
lhcb_rex/models/hetero_graph_based_diffusion_model_simpler.py
lhcb_rex/models/hetero_graph_based_diffusion_model_smearing.py
lhcb_rex/models/model_handler.py
lhcb_rex/models/vanilla_GAN.py
lhcb_rex/models/vanilla_diffusion.py
lhcb_rex/processing/conditional_vars.py
lhcb_rex/processing/min_maxes.pkl
lhcb_rex/processing/processing_tools.py
lhcb_rex/processing/transfomer_quantiles.pkl
lhcb_rex/processing/transformers.py
lhcb_rex/rapidsim/rapidsim_tools.py
lhcb_rex/rapidsim/run_rapidsim.py
lhcb_rex/settings/PVsmear_model_parameters.json
lhcb_rex/settings/default_model_parameters.json
lhcb_rex/settings/diffusion_model_parameters.json
lhcb_rex/settings/diffusion_model_parameters_vtx.json
lhcb_rex/settings/globals.py
lhcb_rex/settings/smear_diffusion_model_parameters.json
lhcb_rex/settings/smearing_model_parameters.json
lhcb_rex/tests/test_basic.py
lhcb_rex/tools/display.py
lhcb_rex/tools/get_weights.py
lhcb_rex/tools/stopwatch.py
lhcb_rex/tools/tuple_tools.py
lhcb_rex/tools/variables_tools.py
lhcb_rex/training/dataloader_handler.py
lhcb_rex/training/hetero_trainer.py
lhcb_rex/training/train.py
lhcb_rex/training/trainer.py
lhcb_rex-0.1.5.dist-info/METADATA
lhcb_rex-0.1.5.dist-info/WHEEL
lhcb_rex-0.1.5.dist-info/top_level.txt
lhcb_rex-0.1.5.dist-info/RECORD
