Metadata-Version: 2.1
Name: lhcb-rex
Version: 0.1.5
Summary: Generalised graph neural network based fast simulation tool for LHCb.
Author-email: Alex Marshall <alex.marshall@cern.ch>
Requires-Python: >=3.9
Requires-Dist: appdirs >=1.4.4
Requires-Dist: geomloss >=0.2.6
Requires-Dist: huggingface-hub ==0.32.4
Requires-Dist: safetensors ==0.5.3
Requires-Dist: diffusers ==0.33.1
Requires-Dist: matplotlib >=3.9.4
Requires-Dist: pandas >=2.3.1
Requires-Dist: pip >=25.1.1
Requires-Dist: psutil >=7.0.0
Requires-Dist: pydantic >=2.11.7
Requires-Dist: pytest >=8.3.5
Requires-Dist: pytorch-lightning ==2.3.3
Requires-Dist: rich >=14.1.0
Requires-Dist: scikit-learn ==1.4.1.post1
Requires-Dist: tensorboard >=2.20.0
Requires-Dist: termcolor >=3.1.0
Requires-Dist: torch ==2.0.1
Requires-Dist: torch-geometric ==2.6.1
Requires-Dist: tqdm >=4.67.1
Requires-Dist: uproot >=5.5.2
Requires-Dist: uproot3 >=3.14.4
Requires-Dist: vector ==0.8.0
